python_cookiecutter/__init__.py
python_cookiecutter/console.py
python_cookiecutter/wikipedia.py
python_cookiecutter-0.1.0.dist-info/entry_points.txt
python_cookiecutter-0.1.0.dist-info/LICENSE
python_cookiecutter-0.1.0.dist-info/WHEEL
python_cookiecutter-0.1.0.dist-info/METADATA
python_cookiecutter-0.1.0.dist-info/RECORD
