Metadata-Version: 2.1
Name: python-cookiecutter
Version: 0.1.0
Summary: The hypermodern Python project
Home-page: https://github.com/udeepam/python-cookiecutter
License: MIT
Keywords: hypermodern
Author: udeepam
Author-email: udeepa652@gmail.com
Requires-Python: >=3.7,<4.0
Classifier: License :: OSI Approved :: MIT License
Classifier: Programming Language :: Python :: 3
Classifier: Programming Language :: Python :: 3.10
Classifier: Programming Language :: Python :: 3.7
Classifier: Programming Language :: Python :: 3.8
Classifier: Programming Language :: Python :: 3.9
Requires-Dist: click (>=8.0.3,<9.0.0)
Requires-Dist: desert (>=2020.11.18,<2021.0.0)
Requires-Dist: marshmallow (>=3.14.1,<4.0.0)
Requires-Dist: requests (>=2.27.1,<3.0.0)
Project-URL: Repository, https://github.com/udeepam/python-cookiecutter
